ninjadog/__init__.py
ninjadog/cli.py
ninjadog/constants.py
ninjadog/decorators.py
ninjadog/ninjadog.py
ninjadog/utils.py
ninjadog/ext/__init__.py
ninjadog/ext/pyramid.py
ninjadog-0.5.2.dist-info/DESCRIPTION.rst
ninjadog-0.5.2.dist-info/METADATA
ninjadog-0.5.2.dist-info/RECORD
ninjadog-0.5.2.dist-info/WHEEL
ninjadog-0.5.2.dist-info/entry_points.txt
ninjadog-0.5.2.dist-info/metadata.json
ninjadog-0.5.2.dist-info/top_level.txt
tests/__init__.py
tests/test_cli.py
tests/test_ninjadog.py
tests/pyramid/test_pyramid.py
tests/pyramid/templates/child.pug
tests/pyramid/templates/parent.pug
