Metadata-Version: 2.0
Name: ninjadog
Version: 0.5.2
Summary: Pug template support in Python
Home-page: https://github.com/knowsuchagency/ninjadog
Author: Stephan Fitzpatrick
Author-email: knowsuchagency@gmail.com
License: MIT license
Keywords: ninjadog,pug,jinja2,html,templating
Platform: UNKNOWN
Classifier: Development Status :: 4 - Beta
Classifier: License :: OSI Approved :: MIT License
Classifier: Natural Language :: English
Classifier: Programming Language :: Python :: 3.5
Classifier: Programming Language :: Python :: 3.6
Requires-Dist: docopt (==0.6.2)
Requires-Dist: jinja2 (==2.9.6)
Requires-Dist: pyramid (==1.9)
Provides-Extra: dev
Requires-Dist: bumpversion (==0.5.3); extra == 'dev'
Requires-Dist: coverage (==4.4.1); extra == 'dev'
Requires-Dist: cryptography (==1.9); extra == 'dev'
Requires-Dist: fabric3 (==1.13.1.post1); extra == 'dev'
Requires-Dist: flake8 (==3.3.0); extra == 'dev'
Requires-Dist: mypy (==0.511); extra == 'dev'
Requires-Dist: pytest; extra == 'dev'
Requires-Dist: pytest-runner (==2.11.1); extra == 'dev'
Requires-Dist: pyyaml (==3.12); extra == 'dev'
Requires-Dist: recommonmark (==0.4.0); extra == 'dev'
Requires-Dist: sphinx (==1.6.2); extra == 'dev'
Requires-Dist: sphinx-autodoc-typehints (==1.2.0); extra == 'dev'
Requires-Dist: tox (==2.7.0); extra == 'dev'
Requires-Dist: watchdog (==0.8.3); extra == 'dev'
Requires-Dist: webtest; extra == 'dev'
Requires-Dist: wheel (==0.29.0); extra == 'dev'
